odysseyz_ovmcp/__init__.py
odysseyz_ovmcp-0.1.5.dist-info/METADATA
odysseyz_ovmcp-0.1.5.dist-info/WHEEL
odysseyz_ovmcp-0.1.5.dist-info/entry_points.txt
odysseyz_ovmcp-0.1.5.dist-info/RECORD
