Metadata-Version: 2.4
Name: odysseyz-ovmcp
Version: 0.1.5
Summary: Add your description here
Requires-Python: >=3.13
Requires-Dist: mcp[cli]>=1.9.4
